isospec_data_tools/__init__.py
isospec_data_tools/analysis/README.md
isospec_data_tools/analysis/__init__.py
isospec_data_tools/analysis/classifiers.py
isospec_data_tools/analysis/clustering.py
isospec_data_tools/analysis/confounder_analyzer.py
isospec_data_tools/analysis/glycowork_wrapper.py
isospec_data_tools/analysis/core/README.md
isospec_data_tools/analysis/core/__init__.py
isospec_data_tools/analysis/core/effect_sizes.py
isospec_data_tools/analysis/core/multiple_comparisons.py
isospec_data_tools/analysis/core/project_config.py
isospec_data_tools/analysis/core/statistical_tests.py
isospec_data_tools/analysis/modeling/README.md
isospec_data_tools/analysis/modeling/__init__.py
isospec_data_tools/analysis/modeling/clustering.py
isospec_data_tools/analysis/modeling/model_evaluation.py
isospec_data_tools/analysis/preprocessing/README.md
isospec_data_tools/analysis/preprocessing/__init__.py
isospec_data_tools/analysis/preprocessing/normalizers.py
isospec_data_tools/analysis/preprocessing/pipeline.py
isospec_data_tools/analysis/preprocessing/transformers.py
isospec_data_tools/analysis/preprocessing/validators.py
isospec_data_tools/analysis/specialized/README.md
isospec_data_tools/analysis/specialized/__init__.py
isospec_data_tools/analysis/specialized/ancova_analysis.py
isospec_data_tools/analysis/specialized/confounder_analysis.py
isospec_data_tools/analysis/specialized/glycowork_integration.py
isospec_data_tools/analysis/utils/__init__.py
isospec_data_tools/analysis/utils/data_helpers.py
isospec_data_tools/analysis/utils/exceptions.py
isospec_data_tools/io_utils/__init__.py
isospec_data_tools/io_utils/io_analyze.py
isospec_data_tools/io_utils/mzmine.py
isospec_data_tools/sst_validation/README.md
isospec_data_tools/sst_validation/__init__.py
isospec_data_tools/sst_validation/errors.py
isospec_data_tools/sst_validation/run_validation.py
isospec_data_tools/sst_validation/system_suitability.py
isospec_data_tools/sst_validation/metrics/__init__.py
isospec_data_tools-0.0.4.dist-info/METADATA
isospec_data_tools-0.0.4.dist-info/WHEEL
isospec_data_tools-0.0.4.dist-info/RECORD
