Metadata-Version: 2.4
Name: isospec-data-tools
Version: 0.0.4
Summary: Omics data utilities
Project-URL: Homepage, https://isospec.github.io/isospec-data-tools/
Project-URL: Repository, https://github.com/isospec/isospec-data-tools
Project-URL: Documentation, https://isospec.github.io/isospec-data-tools/
Author-email: Isospec Analytics <dev@isospec.bio>
Keywords: python
Classifier: Intended Audience :: Developers
Classifier: Programming Language :: Python
Classifier: Programming Language :: Python :: 3
Classifier: Programming Language :: Python :: 3.10
Classifier: Programming Language :: Python :: 3.11
Classifier: Programming Language :: Python :: 3.12
Classifier: Programming Language :: Python :: 3.13
Classifier: Topic :: Software Development :: Libraries :: Python Modules
Requires-Python: <4.0,>=3.9
Requires-Dist: glycowork>=1.6.2
Requires-Dist: matplotlib>=3.7.0
Requires-Dist: numpy>=1.24.0
Requires-Dist: pandas>=2.0.0
Requires-Dist: pingouin>=0.5.5
Requires-Dist: scikit-learn>=1.6.1
Requires-Dist: scipy>=1.13.1
Requires-Dist: seaborn>=0.12.0
Requires-Dist: statsmodels>=0.14.5
